Metadata-Version: 2.4
Name: adbfucker
Version: 0.1.0
Summary: Tool for Android ADB automation with image recognition
Home-page: https://github.com/pedrogazil/adbfucker
Author: pedrogazil
Author-email: pdrohenrique353@gmail.com
Classifier: Programming Language :: Python :: 3
Classifier: License :: OSI Approved :: MIT License
Classifier: Operating System :: OS Independent
Requires-Python: >=3.8
License-File: LICENSE
Requires-Dist: opencv-python>=4.5.0
Dynamic: author
Dynamic: author-email
Dynamic: classifier
Dynamic: description
Dynamic: description-content-type
Dynamic: home-page
Dynamic: license-file
Dynamic: requires-dist
Dynamic: requires-python
Dynamic: summary
